history.py
reading.py
response.py
title.py
word_list.py
word_test.py
libs/common.py
libs/newdate.py
engly-0.2.3.dist-info/LICENSE
engly-0.2.3.dist-info/METADATA
engly-0.2.3.dist-info/WHEEL
engly-0.2.3.dist-info/entry_points.txt
engly-0.2.3.dist-info/top_level.txt
engly-0.2.3.dist-info/RECORD
