Metadata-Version: 2.1
Name: engly
Version: 0.2.3
Summary: English Learning Application
Author-email: nanp1311 <pengin.na11@gmail.com>
Project-URL: Homepage, https://github.com/nanp1311/engly
Project-URL: Bug Tracker, https://github.com/nanp1311/engly/issues
Classifier: Programming Language :: Python :: 3
Classifier: License :: OSI Approved :: MIT License
Classifier: Operating System :: OS Independent
Requires-Python: >=3.8
License-File: LICENSE
Requires-Dist: openai ~=0.28
Requires-Dist: wxPython ~=4.2.1
Requires-Dist: plotly ~=5.16.1
